fold_bdd/__init__.py
fold_bdd/folds.py
fold_bdd/test_folds.py
fold_bdd-0.6.0.dist-info/LICENSE
fold_bdd-0.6.0.dist-info/WHEEL
fold_bdd-0.6.0.dist-info/METADATA
fold_bdd-0.6.0.dist-info/RECORD
